datasette_write_ui/__init__.py
datasette_write_ui/routes.py
datasette_write_ui/static/table.css
datasette_write_ui/static/table.min.js
datasette_write_ui/templates/table.html
datasette_write_ui-0.0.1a14.dist-info/licenses/LICENSE
tests/test_datasette_write_ui.py
datasette_write_ui-0.0.1a14.dist-info/METADATA
datasette_write_ui-0.0.1a14.dist-info/WHEEL
datasette_write_ui-0.0.1a14.dist-info/entry_points.txt
datasette_write_ui-0.0.1a14.dist-info/top_level.txt
datasette_write_ui-0.0.1a14.dist-info/RECORD
