Metadata-Version: 2.4
Name: datasette-write-ui
Version: 0.0.1a14
Summary: Datasette UI plugin for editing and inserting rows
Author: Alex Garcia
License-Expression: Apache-2.0
Project-URL: Homepage, https://github.com/datasette/datasettewrite-ui
Project-URL: Changelog, https://github.com/datasette/datasettewrite-ui/releases
Project-URL: Issues, https://github.com/datasette/datasettewrite-ui/issues
Project-URL: CI, https://github.com/datasette/datasettewrite-ui/actions
Classifier: Framework :: Datasette
Requires-Python: >=3.10
License-File: LICENSE
Requires-Dist: datasette>=1.0a21
Requires-Dist: sqlite-utils>=3.38
Provides-Extra: test
Requires-Dist: pytest; extra == "test"
Requires-Dist: pytest-asyncio; extra == "test"
Dynamic: license-file
